LICENSE
MANIFEST.in
README.rst
setup.py
HerklosBotsCore.egg-info/PKG-INFO
HerklosBotsCore.egg-info/SOURCES.txt
HerklosBotsCore.egg-info/dependency_links.txt
HerklosBotsCore.egg-info/requires.txt
HerklosBotsCore.egg-info/top_level.txt
botcore/__init__.py
botcore/main.py
botcore/config/__init__.py
botcore/config/config.py
botcore/services/__init__.py
botcore/social/__init__.py
botcore/util/__init__.py
botcore/util/image_util.py
botcore/util/logging_tool.py
botcore/web/__init__.py