Metadata-Version: 1.1
Name: HerklosBotsCore
Version: 0.0.2
Summary: Herklos Bot Core
Home-page: https://github.com/Herklos-Bots/BotCore
Author: Herklos
Author-email: herklos-bot@protonmail.com
License: UNKNOWN
Keywords: herklos bot core
Platform: UNKNOWN
Classifier: Development Status :: 3 - Alpha
Classifier: Intended Audience :: Developers
Classifier: Topic :: Software Development :: Build Tools
Classifier: License :: OSI Approved :: MIT License
Classifier: Programming Language :: Python :: 3
Classifier: Programming Language :: Python :: 3.4
Classifier: Programming Language :: Python :: 3.5
Classifier: Programming Language :: Python :: 3.6
